LICENSE
MANIFEST.in
README.md
pyproject.toml
setup.py
zengl_playground/__init__.py
zengl_playground/camera.py
zengl_playground/console.py
zengl_playground/framebuffer.py
zengl_playground/playground.py
zengl_playground/uniform_buffer.py
zengl_playground.egg-info/PKG-INFO
zengl_playground.egg-info/SOURCES.txt
zengl_playground.egg-info/dependency_links.txt
zengl_playground.egg-info/requires.txt
zengl_playground.egg-info/top_level.txt
zengl_playground/renderers/background.py
zengl_playground/renderers/cursor.py
zengl_playground/renderers/font.py
zengl_playground/renderers/grid.py
zengl_playground/renderers/logo.py
zengl_playground/resources/__init__.py
zengl_playground/resources/cursors/bracket_a_vertical.png
zengl_playground/resources/cursors/busy_hourglass_outline.png
zengl_playground/resources/cursors/cursor_none.png
zengl_playground/resources/cursors/disabled.png
zengl_playground/resources/cursors/dot_large.png
zengl_playground/resources/cursors/drawing_bucket.png
zengl_playground/resources/cursors/drawing_picker.png
zengl_playground/resources/cursors/hand_closed.png
zengl_playground/resources/cursors/hand_open.png
zengl_playground/resources/cursors/hand_point.png
zengl_playground/resources/cursors/license.txt
zengl_playground/resources/cursors/lock.png
zengl_playground/resources/cursors/lock_unlocked.png
zengl_playground/resources/cursors/look_c.png
zengl_playground/resources/cursors/message_dots_square.png
zengl_playground/resources/cursors/pointer_c.png
zengl_playground/resources/cursors/resize_b_cross.png
zengl_playground/resources/cursors/resize_b_cross_diagonal.png
zengl_playground/resources/cursors/rotate_ccw.png
zengl_playground/resources/cursors/rotate_cw.png
zengl_playground/resources/cursors/steps.png
zengl_playground/resources/cursors/target_a.png
zengl_playground/resources/cursors/zoom_in.png
zengl_playground/resources/cursors/zoom_out.png
zengl_playground/resources/roboto-mono/license.txt
zengl_playground/resources/roboto-mono/roboto-mono.json
zengl_playground/resources/roboto-mono/roboto-mono.ttf